webex_bot/__init__.py
webex_bot/exceptions.py
webex_bot/formatting.py
webex_bot/webex_bot.py
webex_bot/cards/__init__.py
webex_bot/commands/__init__.py
webex_bot/commands/echo.py
webex_bot/commands/help.py
webex_bot/models/__init__.py
webex_bot/models/command.py
webex_bot/models/response.py
webex_bot/websockets/__init__.py
webex_bot/websockets/webex_websocket_client.py
webex_bot-1.0.8.dist-info/licenses/LICENSE
webex_bot-1.0.8.dist-info/METADATA
webex_bot-1.0.8.dist-info/WHEEL
webex_bot-1.0.8.dist-info/top_level.txt
webex_bot-1.0.8.dist-info/RECORD
