Metadata-Version: 2.4
Name: webex_bot
Version: 1.0.8
Summary: Python package for a Webex Bot based on websockets.
Home-page: https://github.com/fbradyirl/webex_bot
Author: Finbarr Brady
Author-email: finbarr@somemail.com
License: MIT license
Keywords: webex_bot
Classifier: Development Status :: 2 - Pre-Alpha
Classifier: Intended Audience :: Developers
Classifier: License :: OSI Approved :: MIT License
Classifier: Natural Language :: English
Classifier: Programming Language :: Python :: 3.10
Classifier: Programming Language :: Python :: 3.11
Classifier: Programming Language :: Python :: 3.12
Classifier: Programming Language :: Python :: 3.13
Requires-Python: >=3.10
License-File: LICENSE
Requires-Dist: webexpythonsdk==2.0.4
Requires-Dist: coloredlogs
Requires-Dist: websockets==11.0.3
Requires-Dist: backoff
Provides-Extra: proxy
Requires-Dist: websockets_proxy>=0.1.1; extra == "proxy"
Dynamic: author
Dynamic: author-email
Dynamic: classifier
Dynamic: description
Dynamic: description-content-type
Dynamic: home-page
Dynamic: keywords
Dynamic: license
Dynamic: license-file
Dynamic: provides-extra
Dynamic: requires-dist
Dynamic: requires-python
Dynamic: summary
